fantasynames/__init__.py
fantasynames/anglo.py
fantasynames/data.py
fantasynames/dwarf.py
fantasynames/elf.py
fantasynames/french.py
fantasynames/hobbit.py
fantasynames/human_diverse.py
fantasynames/language.py
fantasynames-0.1.1.dist-info/WHEEL
fantasynames-0.1.1.dist-info/METADATA
fantasynames-0.1.1.dist-info/RECORD
