Metadata-Version: 2.1
Name: fantasynames
Version: 0.1.1
Summary: A fantasy themed random name generator.
Home-page: https://github.com/jessypeck/fantasynames
Author: Jessica Peck
Author-email: jessypeck@gmail.com
Requires-Python: >=3.7,<4.0
Classifier: Programming Language :: Python :: 3
Classifier: Programming Language :: Python :: 3.7
Classifier: Programming Language :: Python :: 3.8
Classifier: Programming Language :: Python :: 3.9
Requires-Dist: black (>=20.8b1,<21.0)
Requires-Dist: flake8 (>=3.9.0,<4.0.0)
Requires-Dist: mypy (>=0.812,<0.813)
Project-URL: Repository, https://github.com/jessypeck/fantasynames
